{
    "questions": [
        {
            "questionId": 0,
            "questionContent": "In what year was Sega Genesis released in North America?",
            "questionOptions": [
                "1989",
                "1999",
                "1975",
                "1991"
            ]
        },
        {
            "questionId": 1,
            "questionContent": "Which of the following video games takes place in a dystopian underwater city called Rapture?",
            "questionOptions": [
                "Bioshock",
                "Half-Life",
                "God Of War",
                "Fallout 3"
            ]
        },
        {
            "questionId": 2,
            "questionContent": "What Nintendo system was released after the N64 and before the Wii?",
            "questionOptions": [
                "Gamecube",
                "Nintendo 128",
                "Virtual Boy",
                "Super Nintendo"
            ]
        },
        {
            "questionId": 3,
            "questionContent": "Honda, Dhalsim and Chun Li are all characters from what video game series?",
            "questionOptions": [
                "Street Fighter",
                "Teenage Mutant Ninja Turtles",
                "Battletoads",
                "Mortal Kombat"
            ]
        },
        {
            "questionId": 4,
            "questionContent": "What color is the ring of death on an XBOX that signifies a hardware failure?",
            "questionOptions": [
                "Red",
                "Blue",
                "Yellow",
                "Green"
            ]
        },
        {
            "questionId": 5,
            "questionContent": "What classic beat-'em-up game featured brothers Billy Lee and Jimmy (also nicknamed Spike and Hammer)?",
            "questionOptions": [
                "Double Dragon",
                "Smash Brothers",
                "Ninja Gaiden",
                "Snow Brothers"
            ]
        },
        {
            "questionId": 6,
            "questionContent": "How many bits was the Super Nintendo Entertainment System?",
            "questionOptions": [
                "16",
                "8",
                "128",
                "64"
            ]
        },
        {
            "questionId": 7,
            "questionContent": "What character do you play as in The Legend Of Zelda?",
            "questionOptions": [
                "Link",
                "Gandolf",
                "Chimmy",
                "Peter"
            ]
        },
        {
            "questionId": 8,
            "questionContent": "What 64-bit Sega system was a predecessor to the PlayStation and Nintendo 64?",
            "questionOptions": [
                "Saturn",
                "Dreamcast",
                "Commodore 128",
                "3DO"
            ]
        },
        {
            "questionId": 9,
            "questionContent": "The game Grand Theft Auto was released primarily for what gaming system?",
            "questionOptions": [
                "PlayStation",
                "Dreamcast",
                "XBOX",
                "NES"
            ]
        },
        {
            "questionId": 10,
            "questionContent": "Which James Bond film was made into a game for the Nintendo 64 console and later for the Wii console?",
            "questionOptions": [
                "Goldeneye",
                "Thunderball",
                "Moonraker",
                "Goldfinger"
            ]
        },
        {
            "questionId": 11,
            "questionContent": "Which popular video game features an ex-Special Forces operator named Jack Carver, who is stranded in Micronesia?",
            "questionOptions": [
                "Far Cry",
                "Halo 2",
                "Left 4 Dead",
                "Max Payne"
            ]
        }
    ]
}